caniscrape/__init__.py
caniscrape/cli.py
caniscrape/analyzers/__init__.py
caniscrape/analyzers/behavioral_detector.py
caniscrape/analyzers/captcha_detector.py
caniscrape/analyzers/fingerprint_analyzer.py
caniscrape/analyzers/integrity_analyzer.py
caniscrape/analyzers/js_detector.py
caniscrape/analyzers/rate_limit_profiler.py
caniscrape/analyzers/robots_checker.py
caniscrape/analyzers/tls_analyzer.py
caniscrape/analyzers/waf_detector.py
caniscrape/recommendations/__init__.py
caniscrape/recommendations/recommender.py
caniscrape/scoring/__init__.py
caniscrape/scoring/scoring_engine.py
caniscrape/utils/__init__.py
caniscrape/utils/browser_identities.py
caniscrape/utils/captcha_solvers.py
caniscrape/utils/impersonate_target.py
caniscrape/utils/waf_result_parser.py
caniscrape-0.3.0.dist-info/licenses/LICENSE
caniscrape-0.3.0.dist-info/METADATA
caniscrape-0.3.0.dist-info/WHEEL
caniscrape-0.3.0.dist-info/entry_points.txt
caniscrape-0.3.0.dist-info/top_level.txt
caniscrape-0.3.0.dist-info/RECORD
