Metadata-Version: 2.4
Name: caniscrape
Version: 0.3.0
Summary: Analyze website anti-bot protections before you scrape
Home-page: https://github.com/ZA1815/caniscrape
Author: Zaid Ahmed
Author-email: zaahme18@gmail.com
License: MIT
Classifier: Development Status :: 4 - Beta
Classifier: Intended Audience :: Developers
Classifier: Topic :: Software Development :: Libraries :: Python Modules
Classifier: Programming Language :: Python :: 3
Classifier: Programming Language :: Python :: 3.9
Classifier: Programming Language :: Python :: 3.10
Classifier: Programming Language :: Python :: 3.11
Classifier: Programming Language :: Python :: 3.12
Classifier: Programming Language :: Python :: 3.13
Requires-Python: >=3.9
License-File: LICENSE
Requires-Dist: click>=8.0.0
Requires-Dist: rich>=13.0.0
Requires-Dist: aiohttp>=3.8.0
Requires-Dist: beautifulsoup4>=4.11.0
Requires-Dist: playwright>=1.40.0
Requires-Dist: curl-cffi>=0.5.0
Requires-Dist: requests>=2.28.0
Requires-Dist: aiohttp-socks>=0.7.0
Requires-Dist: capsolver>=1.0.7
Requires-Dist: 2captcha-python>=1.5.1
Dynamic: author
Dynamic: author-email
Dynamic: classifier
Dynamic: description
Dynamic: description-content-type
Dynamic: home-page
Dynamic: license
Dynamic: license-file
Dynamic: requires-dist
Dynamic: requires-python
Dynamic: summary
